hatch_compile_yaml/__init__.py
hatch_compile_yaml/convert.py
hatch_compile_yaml/hooks.py
hatch_compile_yaml/plugin.py
hatch_compile_yaml-18.0.0.dist-info/METADATA
hatch_compile_yaml-18.0.0.dist-info/WHEEL
hatch_compile_yaml-18.0.0.dist-info/entry_points.txt
hatch_compile_yaml-18.0.0.dist-info/RECORD
