Metadata-Version: 2.3
Name: hatch-compile-yaml
Version: 18.0.0
Summary: Compile yaml files to msgpack
Author-email: Tyler Levy Conde <yonstib@gmail.com>
License-Expression: MIT
Classifier: Development Status :: 4 - Beta
Classifier: Framework :: Hatch
Classifier: Programming Language :: Python
Classifier: Programming Language :: Python :: 3.9
Classifier: Programming Language :: Python :: 3.10
Classifier: Programming Language :: Python :: 3.11
Classifier: Programming Language :: Python :: Implementation :: CPython
Classifier: Programming Language :: Python :: Implementation :: PyPy
Requires-Python: >=3.10
Requires-Dist: hatchling
Requires-Dist: msgpack
Requires-Dist: pathspec
Requires-Dist: pyyaml
